karrio/mappers/generic/__init__.py
karrio/mappers/generic/mapper.py
karrio/mappers/generic/proxy.py
karrio/mappers/generic/settings.py
karrio/plugins/generic/__init__.py
karrio/providers/generic/__init__.py
karrio/providers/generic/units.py
karrio/providers/generic/utils.py
karrio_generic-2026.1.4.dist-info/METADATA
karrio_generic-2026.1.4.dist-info/WHEEL
karrio_generic-2026.1.4.dist-info/entry_points.txt
karrio_generic-2026.1.4.dist-info/top_level.txt
karrio_generic-2026.1.4.dist-info/RECORD
